django_db_retry
